cloudpayments/__init__.py
cloudpayments/client.py
cloudpayments/enums.py
cloudpayments/errors.py
cloudpayments/models.py
cloudpayments/tests.py
cloudpayments/utils.py
async_cloudpayments-1.6.6.dist-info/LICENSE
async_cloudpayments-1.6.6.dist-info/METADATA
async_cloudpayments-1.6.6.dist-info/WHEEL
async_cloudpayments-1.6.6.dist-info/top_level.txt
async_cloudpayments-1.6.6.dist-info/RECORD
