Metadata-Version: 2.1
Name: async-cloudpayments
Version: 1.6.6
Summary: CloudPayments Python Client Library (Asynchronous version)
Home-page: https://github.com/ex3lite/aio-cloudpayments-python-client
Download-URL: https://github.com/ex3lite/aio-cloudpayments-python-client/tarball/1.6.6
Author: Antida software
Author-email: info@antidasoftware.com
License: MIT license
Classifier: Development Status :: 4 - Beta
Classifier: Intended Audience :: Developers
Classifier: License :: OSI Approved :: MIT License
Classifier: Programming Language :: Python
Classifier: Programming Language :: Python :: 3
Classifier: Programming Language :: Python :: 3.7
Classifier: Programming Language :: Python :: 3.8
Classifier: Programming Language :: Python :: 3.9
Classifier: Programming Language :: Python :: 3.10
Classifier: Topic :: Office/Business
Classifier: Topic :: Office/Business :: Financial
Classifier: Topic :: Software Development :: Libraries :: Python Modules
License-File: LICENSE
Requires-Dist: aiohttp>=3.7.0
Requires-Dist: pytz>=2015.7
